{
    "total_stars": 41,
    "achievements": {
        "kill_10000_bugs": {
            "description": "Kill 10,000 bugs",
            "target": 10000,
            "progress": 0,
            "star_reward": 1,
            "completed": false
        },
        "earn_100000_cash": {
            "description": "Earn 100,000 cash",
            "target": 100000,
            "progress": 0,
            "star_reward": 2,
            "completed": false
        },
        "round30_mrcheese_only": {
            "description": "Reach round 30 using only MrCheese",
            "target": 30,
            "progress": 0,
            "star_reward": 5,
            "completed": false
        }
    },
    "checkpoint": null
}